Metadata-Version: 2.4
Name: llama-index-readers-reddit
Version: 0.4.0
Summary: llama-index readers reddit integration
Author-email: Your Name <you@example.com>
Maintainer: vanessahlyan
License-Expression: MIT
License-File: LICENSE
Keywords: comments,reddit,search,subreddit
Requires-Python: <4.0,>=3.9
Requires-Dist: llama-index-core<0.14,>=0.13.0
Requires-Dist: praw<8.0,>=7.6
Requires-Dist: prawcore<3.0,>=2.3
Requires-Dist: requests<3.0,>=2.28
Requires-Dist: update-checker<1.0,>=0.18
Requires-Dist: websocket-client<2.0,>=1.5
